gapo_feed_utilities/__init__.py
gapo_feed_utilities-0.1.0.dist-info/entry_points.txt
gapo_feed_utilities-0.1.0.dist-info/WHEEL
gapo_feed_utilities-0.1.0.dist-info/METADATA
gapo_feed_utilities-0.1.0.dist-info/RECORD
