Metadata-Version: 2.1
Name: gapo-feed-utilities
Version: 0.1.0
Summary: 
Author: Your Name
Author-email: nguyentrongphan@gapo.com.vn
Requires-Python: >=3.7,<4.0
Classifier: Programming Language :: Python :: 3
Classifier: Programming Language :: Python :: 3.7
Classifier: Programming Language :: Python :: 3.8
Requires-Dist: logzero (>=1.5.0,<2.0.0)
Requires-Dist: pydantic (>=1.6.1,<2.0.0)
